{"openapi":"3.0.2","info":{"title":"KeyReply AI module Fastapi","description":"KeyReply AI module Fastapi","version":"1.0.1"},"paths":{"/ie/":{"get":{"tags":["Intent-Example"],"summary":"Status","description":"> Show All project (without data)\n\n\n### Keyword Arguments:\n    project_id {str} -- [if provided, will return based on project_id]\n                        (default: {None})\n\n#### Returns:\n    [json] -- [json of trained model]","operationId":"status_ie__get","parameters":[{"required":false,"schema":{"title":"Project Id","type":"string"},"name":"project_id","in":"query"}],"responses":{"200":{"description":"Successful Response","content":{"application/json":{"schema":{}}}},"422":{"description":"Validation Error","content":{"application/json":{"schema":{"$ref":"#/components/schemas/HTTPValidationError"}}}}}}},"/ie/delete":{"delete":{"tags":["Intent-Example"],"summary":"Delete","description":"> Delete Project, will delete all project if model not provided\n> Will delete all model if version_id not provided\n\n### Arguments:\n    project_id {str} -- [project id]\n\n### Keyword Arguments:\n    model_id {str} -- [model uid] (default: {None})\n    version_id {str} -- [version uid] (default: {None})\n\nReturns:\n    [json] -- [all trained model]","operationId":"delete_ie_delete_delete","parameters":[{"required":true,"schema":{"title":"Project Id","type":"string"},"name":"project_id","in":"query"},{"required":false,"schema":{"title":"Model Id","type":"string"},"name":"model_id","in":"query"},{"required":false,"schema":{"title":"Version Id","type":"string"},"name":"version_id","in":"query"}],"responses":{"200":{"description":"Successful Response","content":{"application/json":{"schema":{}}}},"422":{"description":"Validation Error","content":{"application/json":{"schema":{"$ref":"#/components/schemas/HTTPValidationError"}}}}}}},"/ie/import/json":{"post":{"tags":["Intent-Example"],"summary":"Import Json","description":"> Import data with json parameter. \ncall this the method before evaluate or train\n\n### Arguments:\n    project_id {str} -- [project uid]\n    model_id {str} -- [model uid]\n\n### Keyword Arguments:\n    dataset_json {Dataset} -- [description] (default: {None})\n            Example:\n            ```   \n            {\n                \"questions\": [\n                    {\n                        \"question\": \"What is your name?\",\n                        \"answer\": \"I am chatbot.\"\n                    },\n                    {\n                        \"question\": \"What is your name?\",\n                        \"answer\": \"My name is Elsa.\"\n                    }\n                ]\n            }\n            ```\n\n### Returns:\n    [json] -- [data info]","operationId":"import_json_ie_import_json_post","parameters":[{"required":true,"schema":{"title":"Project Id","type":"string"},"name":"project_id","in":"query"},{"required":true,"schema":{"title":"Model Id","type":"string"},"name":"model_id","in":"query"}],"requestBody":{"content":{"application/json":{"schema":{"$ref":"#/components/schemas/QuestionList"}}}},"responses":{"200":{"description":"Successful Response","content":{"application/json":{"schema":{}}}},"422":{"description":"Validation Error","content":{"application/json":{"schema":{"$ref":"#/components/schemas/HTTPValidationError"}}}}}}},"/ie/import":{"post":{"tags":["Intent-Example"],"summary":"Import Data","description":"> Import data to pandas dataframe. \ncall this the method before evaluate or train\n\n### Arguments:\n    project_id {str} -- [project uid]\n    model_id {str} -- [model uid]\n    file {File} -- [multipart file, upload any supported type.\n                    - if file type is text/md, please provide question                                 and answer prefix\n                    - if file type is excel, please provide sheet name\n                    ]\n### Returns:\n    [json] -- [data info]","operationId":"import_data_ie_import_post","parameters":[{"required":true,"schema":{"title":"Project Id","type":"string"},"name":"project_id","in":"query"},{"required":true,"schema":{"title":"Model Id","type":"string"},"name":"model_id","in":"query"},{"required":false,"schema":{"title":"Question Prefix","type":"string"},"name":"question_prefix","in":"query"},{"required":false,"schema":{"title":"Answer Prefix","type":"string"},"name":"answer_prefix","in":"query"},{"required":false,"schema":{"title":"Sheet Name","type":"string"},"name":"sheet_name","in":"query"}],"requestBody":{"content":{"multipart/form-data":{"schema":{"$ref":"#/components/schemas/Body_import_data_ie_import_post"}}},"required":true},"responses":{"200":{"description":"Successful Response","content":{"application/json":{"schema":{}}}},"422":{"description":"Validation Error","content":{"application/json":{"schema":{"$ref":"#/components/schemas/HTTPValidationError"}}}}}}},"/ie/train":{"post":{"tags":["Intent-Example"],"summary":"Train","description":"> Train Intent-Example using json\n\n### Arguments:\n    project_id {str} -- [description]\n    model_id {str} -- [description]\n\n### Keyword Arguments:\n    dataset_json {Dataset} -- [description] (default: {None})\n            Example:\n            ```    \n            {\n                \"intents\": [\n                    {\n                        \"intent_name\": \"OS_VERSION\",\n                        \"examples\": [\n                            \"Which OS version is compatible with                                         ABA Mobile Banking App?\",\n                            \"which Android version that compatible?\",\n                            \"តើប្រព័ន្ធប្រតិបត្តិការណាដែលត្រូវគ្នាជាមួយកម្មវិធីធនាគារអេប៊ីអេ។\"\n                        ]\n                    },\n                    {\n                        \"intent_name\": \"INTERNET_CONNECTION\",\n                        \"examples\": [\n                            \"Is an Internet connection mandatory?\",\n                            \"Can I use it offline?\",\n                            \"តើការតភ្ជាប់អ៊ីនធឺណិតចាំបាច់ទេ?\",\n                            \"តើខ្ញុំអាចប្រើវាក្រៅអ៊ីនធឺណិតបានទេ?\"\n                        ]\n                    },\n                    {\n                        \"intent_name\": \"DOWNLOAD_CHARGE\",\n                        \"examples\": [\n                            \"What are the charges for downloading                                         and using ABA Mobile Banking App?\",\n                            \"តើត្រូវចំណាយប៉ុន្មានដើម្បីដោនឡូតនិងប្រើប្                                        រាស់កម្មវិធីធនាគារចល័តរបស់ធនាគារ ABA?\",\n                            \"តើធនាគារចល័តអេប៊ីអេអាចទាញយកដោយឥតគិតថ្លៃបានទេ?\"\n                        ]\n                    }\n                ]\n            }\n            ```\n    mode {EmbeddingMode} -- [Embedding used to training]                 (default: {EmbeddingMode.USE})\n\n### Returns:\n    [json] -- [info for trained ]","operationId":"train_ie_train_post","parameters":[{"required":true,"schema":{"title":"Project Id","type":"string"},"name":"project_id","in":"query"},{"required":true,"schema":{"title":"Model Id","type":"string"},"name":"model_id","in":"query"},{"required":false,"schema":{"allOf":[{"$ref":"#/components/schemas/EmbeddingMode"}],"default":"USEENG"},"name":"mode","in":"query"}],"requestBody":{"content":{"application/json":{"schema":{"$ref":"#/components/schemas/Dataset"}}}},"responses":{"200":{"description":"Successful Response","content":{"application/json":{"schema":{}}}},"422":{"description":"Validation Error","content":{"application/json":{"schema":{"$ref":"#/components/schemas/HTTPValidationError"}}}}}}},"/ie/train/threaded":{"post":{"tags":["Intent-Example"],"summary":"Train Threaded","description":"> Train Intent-Example using json\n\n### Arguments:\n    project_id {str} -- [description]\n    model_id {str} -- [description]\n\n### Keyword Arguments:\n    dataset_json {Dataset} -- [description] (default: {None})\n            Example:\n            ```    \n            {\n                \"intents\": [\n                    {\n                        \"intent_name\": \"OS_VERSION\",\n                        \"examples\": [\n                            \"Which OS version is compatible with                                         ABA Mobile Banking App?\",\n                            \"which Android version that compatible?\",\n                            \"តើប្រព័ន្ធប្រតិបត្តិការណាដែលត្រូវគ្នាជាមួយកម្មវិធីធនាគារអេប៊ីអេ។\"\n                        ]\n                    },\n                    {\n                        \"intent_name\": \"INTERNET_CONNECTION\",\n                        \"examples\": [\n                            \"Is an Internet connection mandatory?\",\n                            \"Can I use it offline?\",\n                            \"តើការតភ្ជាប់អ៊ីនធឺណិតចាំបាច់ទេ?\",\n                            \"តើខ្ញុំអាចប្រើវាក្រៅអ៊ីនធឺណិតបានទេ?\"\n                        ]\n                    },\n                    {\n                        \"intent_name\": \"DOWNLOAD_CHARGE\",\n                        \"examples\": [\n                            \"What are the charges for downloading                                         and using ABA Mobile Banking App?\",\n                            \"តើត្រូវចំណាយប៉ុន្មានដើម្បីដោនឡូតនិងប្រើប្                                        រាស់កម្មវិធីធនាគារចល័តរបស់ធនាគារ ABA?\",\n                            \"តើធនាគារចល័តអេប៊ីអេអាចទាញយកដោយឥតគិតថ្លៃបានទេ?\"\n                        ]\n                    }\n                ]\n            }\n            ```\n    mode {EmbeddingMode} -- [Embedding used to training]                 (default: {EmbeddingMode.USE})\n\n### Returns:\n    [json] -- [info for trained ]","operationId":"train_threaded_ie_train_threaded_post","parameters":[{"required":true,"schema":{"title":"Project Id","type":"string"},"name":"project_id","in":"query"},{"required":true,"schema":{"title":"Model Id","type":"string"},"name":"model_id","in":"query"},{"required":false,"schema":{"allOf":[{"$ref":"#/components/schemas/EmbeddingMode"}],"default":"USEENG"},"name":"mode","in":"query"}],"requestBody":{"content":{"application/json":{"schema":{"$ref":"#/components/schemas/Dataset"}}}},"responses":{"200":{"description":"Successful Response","content":{"application/json":{"schema":{}}}},"422":{"description":"Validation Error","content":{"application/json":{"schema":{"$ref":"#/components/schemas/HTTPValidationError"}}}}}}},"/ie/train/status":{"get":{"tags":["Intent-Example"],"summary":"Train Status","description":"> get training progress by \n\n### Arguments:\n    project_id {str} -- [project uid]\n    model_id {str} -- [project uid]\n    version_id {str} -- [version id]\n\n### Returns:\n    [json] -- [all loaded model]","operationId":"train_status_ie_train_status_get","parameters":[{"required":false,"schema":{"title":"Project Id","type":"string"},"name":"project_id","in":"query"},{"required":false,"schema":{"title":"Model Id","type":"string"},"name":"model_id","in":"query"}],"responses":{"200":{"description":"Successful Response","content":{"application/json":{"schema":{}}}},"422":{"description":"Validation Error","content":{"application/json":{"schema":{"$ref":"#/components/schemas/HTTPValidationError"}}}}}}},"/ie/predict":{"post":{"tags":["Intent-Example"],"summary":"Predict Return Json","description":"> Predict to make return json\n\n### Arguments:\n    models {Models} -- [list of models that use to predict]\n        example: JSON BODY\n        ```\n            {\n                \"models\": [\n                    {\n                        \"project_id\": \"sample_project\",\n                        \"model_id\": \"sample_model\",\n                        \"version_id\": \"20200213-115918_USE\"\n                    }\n                ]\n            }\n        ```\n    q {str} -- [query string/question]\n\n### Returns:\n    [JSON] -- [respons ranking]","operationId":"predict_return_json_ie_predict_post","parameters":[{"required":true,"schema":{"title":"Q","type":"string"},"name":"q","in":"query"}],"requestBody":{"content":{"application/json":{"schema":{"$ref":"#/components/schemas/Models"}}},"required":true},"responses":{"200":{"description":"Successful Response","content":{"application/json":{"schema":{}}}},"422":{"description":"Validation Error","content":{"application/json":{"schema":{"$ref":"#/components/schemas/HTTPValidationError"}}}}}}},"/ie/predict/text":{"post":{"tags":["Intent-Example"],"summary":"Predict Return Text","description":"> Predict to make return json\n\n### Arguments:\n    models {Models} -- [list of models that use to predict]\n        example: JSON BODY\n        ```\n            {\n                \"models\": [\n                    {\n                        \"project_id\": \"sample_project\",\n                        \"model_id\": \"sample_model\",\n                        \"version_id\": \"20200213-115918_USE\"\n                    }\n                ]\n            }\n        ```\n    q {str} -- [query string/question]\n\n### Returns:\n    [JSON] -- [text]","operationId":"predict_return_text_ie_predict_text_post","parameters":[{"required":true,"schema":{"title":"Q","type":"string"},"name":"q","in":"query"}],"requestBody":{"content":{"application/json":{"schema":{"$ref":"#/components/schemas/Models"}}},"required":true},"responses":{"200":{"description":"Successful Response","content":{"application/json":{"schema":{}}}},"422":{"description":"Validation Error","content":{"application/json":{"schema":{"$ref":"#/components/schemas/HTTPValidationError"}}}}}}},"/ie/evaluate":{"get":{"tags":["Intent-Example"],"summary":"Evaluate","description":"> Evaluate dataset(which has been imported before)\n\n### Arguments:\n    request {Request} -- [request for auth, no need to provide]\n    project_id {str} -- [project_id of data]\n    data_id {str} -- [data_id]\n\n### Keyword Arguments:\n    mode {EmbeddingMode} -- [Embedding type for evaluating]\n                            (default: {EmbeddingMode.USE})\n\n### Returns:\n    CSV File -- [csv file from evaluated]","operationId":"evaluate_ie_evaluate_get","parameters":[{"required":true,"schema":{"title":"Project Id","type":"string"},"name":"project_id","in":"query"},{"required":true,"schema":{"title":"Model Id","type":"string"},"name":"model_id","in":"query"},{"required":true,"schema":{"title":"Data Id","type":"string"},"name":"data_id","in":"query"},{"required":false,"schema":{"allOf":[{"$ref":"#/components/schemas/EmbeddingMode"}],"default":"USEMUL"},"name":"mode","in":"query"}],"responses":{"200":{"description":"Successful Response","content":{"application/json":{"schema":{}}}},"422":{"description":"Validation Error","content":{"application/json":{"schema":{"$ref":"#/components/schemas/HTTPValidationError"}}}}}}},"/ie/evaluate/excel":{"post":{"tags":["Intent-Example"],"summary":"Evaluate Excel","description":"> Evaluate excel file\n\n### Arguments:\n    input_list {List[dict]} -- [list of intent and example pair]\n    Sample (json data):\n    ```                    \n        [\n            {\n                \"Intent\":\"GENERIC_STATEMENT\",\n                \"Example\":\"what is e-posted list?\"\n            },\n            {\n                \"Intent\":\"WITHDRAWAL_SUBMISSION_RM1MIL\",\n                \"Example\":\"Boleh tak saya apply secara online?\"\n            },\n        ]\n    ```\n### Keyword Arguments:\n    mode {EmbeddingMode} -- [embedding mode for evaluation]\n        (default: {EmbeddingMode.USE})\n\n\n### Return item:\n- Similarity = distance to closest data. High is good\n- Intent = source Intent\n- Example = source Example\n- Conflict with = closest intent\n- Similar utterance = closest example\n- Too long = if source example more than 200 (text treshold)\n- Conflict = if source intent is different with closest intent\n- Lack of support = if similarity  < 0.8 (similarity treshold). False is good\n- Good = if not lack of support and not conflict and not too long\n\n\n### Json return sample:\n    ```\n    [\n        {\n            \"Similarity\": 0.2719572820481222,\n            \"Intent\": \"GENERIC_STATEMENT\",\n            \"Example\": \"what is e-posted list?\",\n            \"Conflict with\": \"WITHDRAWAL_EDUCATION_IPP_LIST\",\n            \"Similar utterance\": \"Is PERKESO is on the list?\",\n            \"Too long\": false,\n            \"Conflict\": true,\n            \"Lack of support\": true,\n            \"Good\": false\n        },\n        {\n            \"Similarity\": 0.5256810431267805,\n            \"Intent\": \"WITHDRAWAL_SUBMISSION_RM1MIL\",\n            \"Example\": \"Boleh tak saya apply secara online?\",\n            \"Conflict with\": \"WITHDRAWAL_EDUCATION_STATEMENT_BALANCELOAN\",\n            \"Similar utterance\": \"EKlaau saya print statement melalui online boleh guna tak?\",\n            \"Too long\": false,\n            \"Conflict\": true,\n            \"Lack of support\": true,\n            \"Good\": false\n        }\n    ]\n    ```","operationId":"evaluate_excel_ie_evaluate_excel_post","parameters":[{"required":false,"schema":{"allOf":[{"$ref":"#/components/schemas/EmbeddingMode"}],"default":"USEMUL"},"name":"mode","in":"query"}],"requestBody":{"content":{"application/json":{"schema":{"title":"Input List","type":"array","items":{"type":"object"}}}},"required":true},"responses":{"200":{"description":"Successful Response","content":{"application/json":{"schema":{}}}},"422":{"description":"Validation Error","content":{"application/json":{"schema":{"$ref":"#/components/schemas/HTTPValidationError"}}}}}}},"/ie/evaluate/qbox":{"get":{"tags":["Intent-Example"],"summary":"Evaluate Qbox","description":"> Evaluate dataset(which has been imported before)\n\n### Arguments:\n    request {Request} -- [request for auth, no need to provide]\n    project_id {str} -- [project_id of data]\n    data_id {str} -- [data_id]\n\n### Keyword Arguments:\n    mode {EmbeddingMode} -- [Embedding type for evaluating]\n                            (default: {EmbeddingMode.USE})\n\n### Returns:\n    CSV File -- [csv file from evaluated. formatted as qbox]","operationId":"evaluate_qbox_ie_evaluate_qbox_get","parameters":[{"required":true,"schema":{"title":"Project Id","type":"string"},"name":"project_id","in":"query"},{"required":true,"schema":{"title":"Model Id","type":"string"},"name":"model_id","in":"query"},{"required":true,"schema":{"title":"Data Id","type":"string"},"name":"data_id","in":"query"},{"required":false,"schema":{"allOf":[{"$ref":"#/components/schemas/EmbeddingMode"}],"default":"USEMUL"},"name":"mode","in":"query"}],"responses":{"200":{"description":"Successful Response","content":{"application/json":{"schema":{}}}},"422":{"description":"Validation Error","content":{"application/json":{"schema":{"$ref":"#/components/schemas/HTTPValidationError"}}}}}}},"/ie/load":{"get":{"tags":["Intent-Example"],"summary":"Load","description":"> Load model and dataset\n\n### Arguments:\n    project_id {str} -- [project uid]\n    model_id {str} -- [project uid]\n    version_id {str} -- [version id]\n\n### Returns:\n    [json] -- [all loaded model]","operationId":"load_ie_load_get","parameters":[{"required":true,"schema":{"title":"Project Id","type":"string"},"name":"project_id","in":"query"},{"required":true,"schema":{"title":"Model Id","type":"string"},"name":"model_id","in":"query"},{"required":true,"schema":{"title":"Version Id","type":"string"},"name":"version_id","in":"query"}],"responses":{"200":{"description":"Successful Response","content":{"application/json":{"schema":{}}}},"422":{"description":"Validation Error","content":{"application/json":{"schema":{"$ref":"#/components/schemas/HTTPValidationError"}}}}}}},"/ie/unload":{"get":{"tags":["Intent-Example"],"summary":"Unload","description":"> Unload model and dataset\n\n### Arguments:\n    project_id {str} -- [project uid]\n    model_id {str} -- [project uid]\n    version_id {str} -- [version id]\n\n### Returns:\n    [json] -- [all loaded model]","operationId":"unload_ie_unload_get","parameters":[{"required":true,"schema":{"title":"Project Id","type":"string"},"name":"project_id","in":"query"},{"required":true,"schema":{"title":"Model Id","type":"string"},"name":"model_id","in":"query"},{"required":true,"schema":{"title":"Version Id","type":"string"},"name":"version_id","in":"query"}],"responses":{"200":{"description":"Successful Response","content":{"application/json":{"schema":{}}}},"422":{"description":"Validation Error","content":{"application/json":{"schema":{"$ref":"#/components/schemas/HTTPValidationError"}}}}}}},"/qa/":{"get":{"tags":["Question-Answer"],"summary":"Status","description":"> Show All project (without data)\n\n\n### Keyword Arguments:\n    project_id {str} -- [if provided, will return based on project_id]\n                        (default: {None})\n\n#### Returns:\n    [json] -- [json of trained model]","operationId":"status_qa__get","parameters":[{"required":false,"schema":{"title":"Project Id","type":"string"},"name":"project_id","in":"query"}],"responses":{"200":{"description":"Successful Response","content":{"application/json":{"schema":{}}}},"422":{"description":"Validation Error","content":{"application/json":{"schema":{"$ref":"#/components/schemas/HTTPValidationError"}}}}}}},"/qa/delete":{"delete":{"tags":["Question-Answer"],"summary":"Delete","description":"> Delete Project, will delete all project if model not provided\n> Will delete all model if version_id not provided\n\n### Arguments:\n    project_id {str} -- [project id]\n\n### Keyword Arguments:\n    model_id {str} -- [model uid] (default: {None})\n    version_id {str} -- [version uid] (default: {None})\n\nReturns:\n    [json] -- [all trained model]","operationId":"delete_qa_delete_delete","parameters":[{"required":true,"schema":{"title":"Project Id","type":"string"},"name":"project_id","in":"query"},{"required":false,"schema":{"title":"Model Id","type":"string"},"name":"model_id","in":"query"},{"required":false,"schema":{"title":"Version Id","type":"string"},"name":"version_id","in":"query"}],"responses":{"200":{"description":"Successful Response","content":{"application/json":{"schema":{}}}},"422":{"description":"Validation Error","content":{"application/json":{"schema":{"$ref":"#/components/schemas/HTTPValidationError"}}}}}}},"/qa/delete/data":{"delete":{"tags":["Question-Answer"],"summary":"Delete Data","description":"> Delete Data, will delete all data if model not provided\n> Will delete all model if version_id not provided\n\n### Arguments:\n    project_id {str} -- [project id]\n\n### Keyword Arguments:\n    model_id {str} -- [model uid] (default: {None})\n    version_id {str} -- [version uid] (default: {None})\n\nReturns:\n    [json] -- [all trained model]","operationId":"delete_data_qa_delete_data_delete","parameters":[{"required":true,"schema":{"title":"Project Id","type":"string"},"name":"project_id","in":"query"},{"required":false,"schema":{"title":"Model Id","type":"string"},"name":"model_id","in":"query"},{"required":false,"schema":{"title":"Data Id","type":"string"},"name":"data_id","in":"query"}],"responses":{"200":{"description":"Successful Response","content":{"application/json":{"schema":{}}}},"422":{"description":"Validation Error","content":{"application/json":{"schema":{"$ref":"#/components/schemas/HTTPValidationError"}}}}}}},"/qa/import/json":{"post":{"tags":["Question-Answer"],"summary":"Import Json","description":"> Import data with json parameter. \ncall this the method before evaluate or train\n\n### Arguments:\n    project_id {str} -- [project uid]\n    model_id {str} -- [model uid]\n\n### Keyword Arguments:\n    dataset_json {Dataset} -- [description] (default: {None})\n            Example:\n            ```   \n            {\n                \"questions\": [\n                    {\n                        \"question\": \"What is your name?\",\n                        \"answer\": \"I am chatbot.\"\n                    },\n                    {\n                        \"question\": \"What is your name?\",\n                        \"answer\": \"My name is Elsa.\"\n                    }\n                ]\n            }\n            ```\n\n### Returns:\n    [json] -- [data info]","operationId":"import_json_qa_import_json_post","parameters":[{"required":true,"schema":{"title":"Project Id","type":"string"},"name":"project_id","in":"query"},{"required":true,"schema":{"title":"Model Id","type":"string"},"name":"model_id","in":"query"}],"requestBody":{"content":{"application/json":{"schema":{"$ref":"#/components/schemas/QuestionList"}}}},"responses":{"200":{"description":"Successful Response","content":{"application/json":{"schema":{}}}},"422":{"description":"Validation Error","content":{"application/json":{"schema":{"$ref":"#/components/schemas/HTTPValidationError"}}}}}}},"/qa/import":{"post":{"tags":["Question-Answer"],"summary":"Import Data","description":"> Import data to pandas dataframe. \ncall this the method before evaluate or train\n\n### Arguments:\n    project_id {str} -- [project uid]\n    model_id {str} -- [model uid]\n    file {File} -- [multipart file, upload any supported type.\n                    - if file type is text/md, please provide question                                 and answer prefix\n                    - if file type is excel, please provide sheet name\n                    ]\n### Returns:\n    [json] -- [data info]","operationId":"import_data_qa_import_post","parameters":[{"required":true,"schema":{"title":"Project Id","type":"string"},"name":"project_id","in":"query"},{"required":true,"schema":{"title":"Model Id","type":"string"},"name":"model_id","in":"query"},{"required":false,"schema":{"title":"Question Prefix","type":"string"},"name":"question_prefix","in":"query"},{"required":false,"schema":{"title":"Answer Prefix","type":"string"},"name":"answer_prefix","in":"query"},{"required":false,"schema":{"title":"Sheet Name","type":"string"},"name":"sheet_name","in":"query"}],"requestBody":{"content":{"multipart/form-data":{"schema":{"$ref":"#/components/schemas/Body_import_data_qa_import_post"}}},"required":true},"responses":{"200":{"description":"Successful Response","content":{"application/json":{"schema":{}}}},"422":{"description":"Validation Error","content":{"application/json":{"schema":{"$ref":"#/components/schemas/HTTPValidationError"}}}}}}},"/qa/train":{"post":{"tags":["Question-Answer"],"summary":"Train","description":"> Train Question Example using data_id\n\n### Arguments:\n    project_id {str} -- [project uid]\n    model_id {str} -- [project uid]\n    data_id {str} -- [data id]\n    mode {EmbeddingMode} -- [Embedding used to training]                 (default: {EmbeddingMode.USE})\n\n### Returns:\n    [json] -- [info for trained model]","operationId":"train_qa_train_post","parameters":[{"required":true,"schema":{"title":"Project Id","type":"string"},"name":"project_id","in":"query"},{"required":true,"schema":{"title":"Model Id","type":"string"},"name":"model_id","in":"query"},{"required":true,"schema":{"title":"Data Id","type":"string"},"name":"data_id","in":"query"},{"required":false,"schema":{"allOf":[{"$ref":"#/components/schemas/EmbeddingMode"}],"default":"SENTTRANS"},"name":"mode","in":"query"}],"responses":{"200":{"description":"Successful Response","content":{"application/json":{"schema":{}}}},"422":{"description":"Validation Error","content":{"application/json":{"schema":{"$ref":"#/components/schemas/HTTPValidationError"}}}}}}},"/qa/predict":{"post":{"tags":["Question-Answer"],"summary":"Predict Return Json","description":"> Predict using trained model and query string\n\n### Arguments:\n    models {Models} -- [list of models that use to predict]\n        example: JSON BODY\n        ```\n            {\n                \"models\": [\n                    {\n                        \"project_id\": \"sample_project\",\n                        \"model_id\": \"sample_model\",\n                        \"version_id\": \"20200213-115918_USE\"\n                    }\n                ]\n            }\n        ```\n    q {str} -- [query string/question]\n\n### Returns:\n    [JSON] -- [respons ranking]","operationId":"predict_return_json_qa_predict_post","parameters":[{"required":true,"schema":{"title":"Q","type":"string"},"name":"q","in":"query"}],"requestBody":{"content":{"application/json":{"schema":{"$ref":"#/components/schemas/Models"}}},"required":true},"responses":{"200":{"description":"Successful Response","content":{"application/json":{"schema":{}}}},"422":{"description":"Validation Error","content":{"application/json":{"schema":{"$ref":"#/components/schemas/HTTPValidationError"}}}}}}},"/qa/predict/text":{"post":{"tags":["Question-Answer"],"summary":"Predict Return Text","description":"> Predict using trained model and query string\n\n### Arguments:\n    models {Models} -- [list of models that use to predict]\n        example: JSON BODY\n        ```\n            {\n                \"models\": [\n                    {\n                        \"project_id\": \"sample_project\",\n                        \"model_id\": \"sample_model\",\n                        \"version_id\": \"20200213-115918_USE\"\n                    }\n                ]\n            }\n        ```\n    q {str} -- [query string/question]\n\n### Returns:\n    [JSON] -- [text]","operationId":"predict_return_text_qa_predict_text_post","parameters":[{"required":true,"schema":{"title":"Q","type":"string"},"name":"q","in":"query"}],"requestBody":{"content":{"application/json":{"schema":{"$ref":"#/components/schemas/Models"}}},"required":true},"responses":{"200":{"description":"Successful Response","content":{"application/json":{"schema":{}}}},"422":{"description":"Validation Error","content":{"application/json":{"schema":{"$ref":"#/components/schemas/HTTPValidationError"}}}}}}},"/qa/load":{"get":{"tags":["Question-Answer"],"summary":"Load","description":"> Load model and dataset\n\n### Arguments:\n    project_id {str} -- [project uid]\n    model_id {str} -- [project uid]\n    version_id {str} -- [version id]\n\n### Returns:\n    [json] -- [all loaded model]","operationId":"load_qa_load_get","parameters":[{"required":true,"schema":{"title":"Project Id","type":"string"},"name":"project_id","in":"query"},{"required":true,"schema":{"title":"Model Id","type":"string"},"name":"model_id","in":"query"},{"required":true,"schema":{"title":"Version Id","type":"string"},"name":"version_id","in":"query"}],"responses":{"200":{"description":"Successful Response","content":{"application/json":{"schema":{}}}},"422":{"description":"Validation Error","content":{"application/json":{"schema":{"$ref":"#/components/schemas/HTTPValidationError"}}}}}}},"/qa/unload":{"get":{"tags":["Question-Answer"],"summary":"Unload","description":"> Unload model and dataset\n\n### Arguments:\n    project_id {str} -- [project uid]\n    model_id {str} -- [project uid]\n    version_id {str} -- [version id]\n\n### Returns:\n    [json] -- [all loaded model]","operationId":"unload_qa_unload_get","parameters":[{"required":true,"schema":{"title":"Project Id","type":"string"},"name":"project_id","in":"query"},{"required":true,"schema":{"title":"Model Id","type":"string"},"name":"model_id","in":"query"},{"required":true,"schema":{"title":"Version Id","type":"string"},"name":"version_id","in":"query"}],"responses":{"200":{"description":"Successful Response","content":{"application/json":{"schema":{}}}},"422":{"description":"Validation Error","content":{"application/json":{"schema":{"$ref":"#/components/schemas/HTTPValidationError"}}}}}}},"/da/generate":{"get":{"tags":["Data Augmentation"],"summary":"Generate Text","description":"> Generate text\n\n\n### Keyword Arguments:\n    text {str} -- Text to create augmentation\n    num_output {int} -- Number text output\n    use_back_translation {bool} -- True to activate back translation.                 Default: False.\n    origin {LangCode} -- Language code of source text, set None if not sure                 system will automatically detect the language. (Default: None)\n    dest {LangCode} -- Language code of target text, set None to avoid                 translation. (Default: None)\n\n#### Returns:\n    [json] -- [list of genrated model]","operationId":"generate_text_da_generate_get","parameters":[{"required":true,"schema":{"title":"Text","type":"string"},"name":"text","in":"query"},{"required":false,"schema":{"title":"Num Output","type":"integer","default":5},"name":"num_output","in":"query"},{"required":false,"schema":{"$ref":"#/components/schemas/LangCode"},"name":"origin","in":"query"},{"required":false,"schema":{"$ref":"#/components/schemas/LangCode"},"name":"dest","in":"query"}],"responses":{"200":{"description":"Successful Response","content":{"application/json":{"schema":{}}}},"422":{"description":"Validation Error","content":{"application/json":{"schema":{"$ref":"#/components/schemas/HTTPValidationError"}}}}}}},"/oa/instruct":{"post":{"tags":["Open AI API"],"summary":"Generate Text","description":"> Generate text\n\n\n### Keyword Arguments:\n    prompt {str} -- Text instruction prompt\n    engine {str} -- Model engine to use\n    settings_json {OpenAICreate} -- Settings for hyperparameters\n\n#### Returns:\n    [json] -- [response text]","operationId":"generate_text_oa_instruct_post","parameters":[{"required":true,"schema":{"title":"Engine","type":"string"},"name":"engine","in":"query"}],"requestBody":{"content":{"application/json":{"schema":{"$ref":"#/components/schemas/OpenAICreate"}}},"required":true},"responses":{"200":{"description":"Successful Response","content":{"application/json":{"schema":{}}}},"422":{"description":"Validation Error","content":{"application/json":{"schema":{"$ref":"#/components/schemas/HTTPValidationError"}}}}}}},"/oa/finetune":{"get":{"tags":["Open AI API"],"summary":"Finetune Prediction","description":"> Use fintuned model\n\n\n### Keyword Arguments:\n    prompt {str} -- Text to create augmentation\n    model {int} -- model id\n\n#### Returns:\n    [json] -- [response {str}]","operationId":"finetune_prediction_oa_finetune_get","parameters":[{"required":true,"schema":{"title":"Model","type":"string"},"name":"model","in":"query"}],"requestBody":{"content":{"application/json":{"schema":{"$ref":"#/components/schemas/OpenAICreate"}}},"required":true},"responses":{"200":{"description":"Successful Response","content":{"application/json":{"schema":{}}}},"422":{"description":"Validation Error","content":{"application/json":{"schema":{"$ref":"#/components/schemas/HTTPValidationError"}}}}}}},"/document/":{"get":{"tags":["Document Searching"],"summary":"Status","description":"> Show All project (without data)\n\n\n### Keyword Arguments:\n    project_id {str} -- [if provided, will return based on project_id]\n                        (default: {None})\n\n#### Returns:\n    [json] -- [json of trained model]","operationId":"status_document__get","parameters":[{"required":false,"schema":{"title":"Project Id","type":"string"},"name":"project_id","in":"query"}],"responses":{"200":{"description":"Successful Response","content":{"application/json":{"schema":{}}}},"422":{"description":"Validation Error","content":{"application/json":{"schema":{"$ref":"#/components/schemas/HTTPValidationError"}}}}}}},"/document/delete":{"get":{"tags":["Document Searching"],"summary":"Delete","description":"> Delete Project, will delete all project if model not provided\n> Will delete all model if version_id not provided\n\n### Arguments:\n    project_id {str} -- [project id]\n\n### Keyword Arguments:\n    model_id {str} -- [model uid] (default: {None})\n    version_id {str} -- [version uid] (default: {None})\n\nReturns:\n    [json] -- [all trained model]","operationId":"delete_document_delete_get","parameters":[{"required":true,"schema":{"title":"Project Id","type":"string"},"name":"project_id","in":"query"},{"required":false,"schema":{"title":"Model Id","type":"string"},"name":"model_id","in":"query"},{"required":false,"schema":{"title":"Version Id","type":"string"},"name":"version_id","in":"query"}],"responses":{"200":{"description":"Successful Response","content":{"application/json":{"schema":{}}}},"422":{"description":"Validation Error","content":{"application/json":{"schema":{"$ref":"#/components/schemas/HTTPValidationError"}}}}}}},"/document/train/json":{"post":{"tags":["Document Searching"],"summary":"Train Json","description":"> Train long text and store index\n\n### Arguments:\n    request {Request} -- [description]\n    project_id {str} -- [description]\n    text {str} -- [rawstring text]","operationId":"train_json_document_train_json_post","parameters":[{"required":true,"schema":{"title":"Project Id","type":"string"},"name":"project_id","in":"query"},{"required":true,"schema":{"title":"Model Id","type":"string"},"name":"model_id","in":"query"},{"required":true,"schema":{"title":"Text"},"name":"text","in":"query"}],"responses":{"200":{"description":"Successful Response","content":{"application/json":{"schema":{}}}},"422":{"description":"Validation Error","content":{"application/json":{"schema":{"$ref":"#/components/schemas/HTTPValidationError"}}}}}}},"/document/train":{"post":{"tags":["Document Searching"],"summary":"Train","description":"> Train long text and store index\n\n### Arguments:\n    request {Request} -- [description]\n    project_id {str} -- [description]\n    file {File} -- [file text]","operationId":"train_document_train_post","parameters":[{"required":true,"schema":{"title":"Project Id","type":"string"},"name":"project_id","in":"query"},{"required":true,"schema":{"title":"Model Id","type":"string"},"name":"model_id","in":"query"}],"requestBody":{"content":{"multipart/form-data":{"schema":{"$ref":"#/components/schemas/Body_train_document_train_post"}}},"required":true},"responses":{"200":{"description":"Successful Response","content":{"application/json":{"schema":{}}}},"422":{"description":"Validation Error","content":{"application/json":{"schema":{"$ref":"#/components/schemas/HTTPValidationError"}}}}}}},"/document/predict":{"post":{"tags":["Document Searching"],"summary":"Predict Return Json","description":"> Predict using trained model and query string\n\n### Arguments:\n    models {Models} -- [list of models that use to predict]\n        example: JSON BODY\n        ```\n            {\n                \"models\": [\n                    {\n                        \"project_id\": \"sample_project\",\n                        \"model_id\": \"sample_model\",\n                        \"version_id\": \"20200213-115918_USE\"\n                    }\n                ]\n            }\n        ```\n    q {str} -- [query string/question]\n\n### Returns:\n    [JSON] -- [respons ranking]","operationId":"predict_return_json_document_predict_post","parameters":[{"required":true,"schema":{"title":"Q","type":"string"},"name":"q","in":"query"}],"requestBody":{"content":{"application/json":{"schema":{"$ref":"#/components/schemas/Models"}}},"required":true},"responses":{"200":{"description":"Successful Response","content":{"application/json":{"schema":{}}}},"422":{"description":"Validation Error","content":{"application/json":{"schema":{"$ref":"#/components/schemas/HTTPValidationError"}}}}}}},"/document/predict/text":{"post":{"tags":["Document Searching"],"summary":"Predict Return Text","description":"> Predict using trained model and query string\n\n### Arguments:\n    models {Models} -- [list of models that use to predict]\n        example: JSON BODY\n        ```\n            {\n                \"models\": [\n                    {\n                        \"project_id\": \"sample_project\",\n                        \"model_id\": \"sample_model\",\n                        \"version_id\": \"20200213-115918_USE\"\n                    }\n                ]\n            }\n        ```\n    q {str} -- [query string/question]\n\n### Returns:\n    [text] -- [text of question with most similar]","operationId":"predict_return_text_document_predict_text_post","parameters":[{"required":true,"schema":{"title":"Q","type":"string"},"name":"q","in":"query"}],"requestBody":{"content":{"application/json":{"schema":{"$ref":"#/components/schemas/Models"}}},"required":true},"responses":{"200":{"description":"Successful Response","content":{"application/json":{"schema":{}}}},"422":{"description":"Validation Error","content":{"application/json":{"schema":{"$ref":"#/components/schemas/HTTPValidationError"}}}}}}},"/document/load":{"get":{"tags":["Document Searching"],"summary":"Load Model","description":"> Load model and dataset\n\n### Arguments:\n    project_id {str} -- [project uid]\n    model_id {str} -- [project uid]\n    version_id {str} -- [version id]\n\n### Returns:\n    [json] -- [all loaded model]","operationId":"load_model_document_load_get","parameters":[{"required":true,"schema":{"title":"Project Id","type":"string"},"name":"project_id","in":"query"},{"required":true,"schema":{"title":"Model Id","type":"string"},"name":"model_id","in":"query"},{"required":true,"schema":{"title":"Version Id","type":"string"},"name":"version_id","in":"query"}],"responses":{"200":{"description":"Successful Response","content":{"application/json":{"schema":{}}}},"422":{"description":"Validation Error","content":{"application/json":{"schema":{"$ref":"#/components/schemas/HTTPValidationError"}}}}}}},"/document/unload":{"get":{"tags":["Document Searching"],"summary":"Unload","description":"> Unload model and dataset\n### Arguments:\n    project_id {str} -- [project uid]\n    model_id {str} -- [project uid]\n    version_id {str} -- [version id]\n\n### Returns:\n    [json] -- [all loaded model]","operationId":"unload_document_unload_get","parameters":[{"required":true,"schema":{"title":"Project Id","type":"string"},"name":"project_id","in":"query"},{"required":true,"schema":{"title":"Model Id","type":"string"},"name":"model_id","in":"query"},{"required":true,"schema":{"title":"Version Id","type":"string"},"name":"version_id","in":"query"}],"responses":{"200":{"description":"Successful Response","content":{"application/json":{"schema":{}}}},"422":{"description":"Validation Error","content":{"application/json":{"schema":{"$ref":"#/components/schemas/HTTPValidationError"}}}}}}},"/clustering/cluster":{"get":{"tags":["Clustering"],"summary":"Clustering","description":"> Do Clustering\n\n\n### Keyword Arguments:\n    project_id {str} -- [if provided, will return based on project_id]\n                        (default: {None})\n\n#### Returns:\n    [json] -- [json of trained model]","operationId":"clustering_clustering_cluster_get","parameters":[{"required":true,"schema":{"title":"Project Id","type":"string"},"name":"project_id","in":"query"},{"required":true,"schema":{"title":"Model Id","type":"string"},"name":"model_id","in":"query"}],"requestBody":{"content":{"application/json":{"schema":{"$ref":"#/components/schemas/ListSentence"}}},"required":true},"responses":{"200":{"description":"Successful Response","content":{"application/json":{"schema":{}}}},"422":{"description":"Validation Error","content":{"application/json":{"schema":{"$ref":"#/components/schemas/HTTPValidationError"}}}}}}},"/":{"get":{"summary":"Hello","operationId":"hello__get","responses":{"200":{"description":"Successful Response","content":{"application/json":{"schema":{}}}}}}},"/setting":{"get":{"summary":"Get All Config","description":"> Return all config provided\n\n### Arguments:\n    Empty arguments\n\n### Returns:\n    Dictionary -- All settings in pair key-value\n\n### Header:\n    AuthKey if provided","operationId":"get_all_config_setting_get","responses":{"200":{"description":"Successful Response","content":{"application/json":{"schema":{}}}}}}},"/status":{"get":{"summary":"Get Server Status","description":"> Get server status\n\n### Arguments:\n    Empty arguments\n\n### Returns:\n    JSON -- Json of uptime, memory,cpu and gpu usage","operationId":"get_server_status_status_get","responses":{"200":{"description":"Successful Response","content":{"application/json":{"schema":{}}}}}}}},"components":{"schemas":{"Body_import_data_ie_import_post":{"title":"Body_import_data_ie_import_post","required":["file"],"type":"object","properties":{"file":{"title":"File","type":"string","format":"binary"}}},"Body_import_data_qa_import_post":{"title":"Body_import_data_qa_import_post","required":["file"],"type":"object","properties":{"file":{"title":"File","type":"string","format":"binary"}}},"Body_train_document_train_post":{"title":"Body_train_document_train_post","required":["file"],"type":"object","properties":{"file":{"title":"File","type":"string","format":"binary"}}},"Dataset":{"title":"Dataset","required":["intents"],"type":"object","properties":{"intents":{"title":"Intents","type":"array","items":{"$ref":"#/components/schemas/Intent"}}}},"EmbeddingMode":{"title":"EmbeddingMode","enum":["USEENG","USE","USEMUL","DISTILBERT","BPE","USEQA","SENTTRANS"],"type":"string","description":"An enumeration."},"HTTPValidationError":{"title":"HTTPValidationError","type":"object","properties":{"detail":{"title":"Detail","type":"array","items":{"$ref":"#/components/schemas/ValidationError"}}}},"Intent":{"title":"Intent","required":["intent_name","examples"],"type":"object","properties":{"intent_name":{"title":"Intent Name","type":"string"},"examples":{"title":"Examples","type":"array","items":{"type":"string"}}}},"LangCode":{"title":"LangCode","enum":["zh-CN","es","hi","pt","bn","ru","ja","de","fr","id","th","tl","vi"],"type":"string","description":"An enumeration."},"ListSentence":{"title":"ListSentence","required":["sentences"],"type":"object","properties":{"sentences":{"title":"Sentences","type":"array","items":{"type":"string"}}}},"ModelDetails":{"title":"ModelDetails","required":["project_id","model_id","version_id"],"type":"object","properties":{"project_id":{"title":"Project Id","type":"string"},"model_id":{"title":"Model Id","type":"string"},"version_id":{"title":"Version Id","type":"string"}}},"Models":{"title":"Models","required":["models"],"type":"object","properties":{"models":{"title":"Models","type":"array","items":{"$ref":"#/components/schemas/ModelDetails"}}}},"OpenAICreate":{"title":"OpenAICreate","required":["prompt","temperature","max_tokens","top_p","n","frequency_penalty","presence_penalty","stop"],"type":"object","properties":{"prompt":{"title":"Prompt","type":"string"},"temperature":{"title":"Temperature","type":"number"},"max_tokens":{"title":"Max Tokens","type":"integer"},"top_p":{"title":"Top P","type":"number"},"n":{"title":"N","type":"integer"},"logprobs":{"title":"Logprobs","type":"integer"},"frequency_penalty":{"title":"Frequency Penalty","type":"number"},"presence_penalty":{"title":"Presence Penalty","type":"number"},"stop":{"title":"Stop","type":"array","items":{"type":"string"}}}},"Question":{"title":"Question","required":["question","answer"],"type":"object","properties":{"question":{"title":"Question","type":"string"},"answer":{"title":"Answer","type":"string"}}},"QuestionList":{"title":"QuestionList","required":["questions"],"type":"object","properties":{"questions":{"title":"Questions","type":"array","items":{"$ref":"#/components/schemas/Question"}}}},"ValidationError":{"title":"ValidationError","required":["loc","msg","type"],"type":"object","properties":{"loc":{"title":"Location","type":"array","items":{"type":"string"}},"msg":{"title":"Message","type":"string"},"type":{"title":"Error Type","type":"string"}}}}}}